mineop.py
mineop-1.0.0.dist-info/WHEEL
mineop-1.0.0.dist-info/METADATA
mineop-1.0.0.dist-info/RECORD
