Metadata-Version: 2.1
Name: mineop
Version: 1.0.0
Summary: Welcome()
Author: ALEX9595YT
Requires-Python: >=3.6,<4.0
Classifier: Programming Language :: Python :: 3
Classifier: Programming Language :: Python :: 3.6
Classifier: Programming Language :: Python :: 3.7
Classifier: Programming Language :: Python :: 3.8
